LICENSE
README.md
setup.py
exCvxpy/__init__.py
exCvxpy.egg-info/PKG-INFO
exCvxpy.egg-info/SOURCES.txt
exCvxpy.egg-info/dependency_links.txt
exCvxpy.egg-info/requires.txt
exCvxpy.egg-info/top_level.txt
exCvxpy/atom_canonicalizers/__init__.py
exCvxpy/atom_canonicalizers/tr_inv_canon.py
exCvxpy/atoms/__init__.py
exCvxpy/atoms/tr_inv.py