Metadata-Version: 2.1
Name: exCvxpy
Version: 0.1.2
Summary: A cvxpy extension that adds some atomic operations
Home-page: https://github.com/imcjp/exCvxpy
Author: Cai Jianping
Author-email: jpingcai@163.com
License: MIT Licence
Keywords: cvxpy,optimization
Platform: any
License-File: LICENSE
